odoo/addons/l10n_nl_bsn/README.rst
odoo/addons/l10n_nl_bsn/__init__.py
odoo/addons/l10n_nl_bsn/__manifest__.py
odoo/addons/l10n_nl_bsn/i18n/l10n_nl_bsn.pot
odoo/addons/l10n_nl_bsn/i18n/nl.po
odoo/addons/l10n_nl_bsn/models/__init__.py
odoo/addons/l10n_nl_bsn/models/res_partner.py
odoo/addons/l10n_nl_bsn/readme/CONFIGURE.rst
odoo/addons/l10n_nl_bsn/readme/CONTRIBUTORS.rst
odoo/addons/l10n_nl_bsn/readme/DESCRIPTION.rst
odoo/addons/l10n_nl_bsn/readme/INSTALL.rst
odoo/addons/l10n_nl_bsn/readme/ROADMAP.rst
odoo/addons/l10n_nl_bsn/readme/USAGE.rst
odoo/addons/l10n_nl_bsn/static/description/icon.png
odoo/addons/l10n_nl_bsn/static/description/index.html
odoo/addons/l10n_nl_bsn/tests/__init__.py
odoo/addons/l10n_nl_bsn/tests/test_l10n_nl_bsn.py
odoo/addons/l10n_nl_bsn/views/res_partner.xml
odoo14_addon_l10n_nl_bsn-14.0.1.0.1.dev5.dist-info/METADATA
odoo14_addon_l10n_nl_bsn-14.0.1.0.1.dev5.dist-info/WHEEL
odoo14_addon_l10n_nl_bsn-14.0.1.0.1.dev5.dist-info/top_level.txt
odoo14_addon_l10n_nl_bsn-14.0.1.0.1.dev5.dist-info/RECORD
